{
	"description": "项目配置文件。",
	"setting": {
		"urlCheck": false,
		"es6": true,
		"postcss": true,
		"minified": true,
		"newFeature": true
	},
	"compileType": "miniprogram",
	"libVersion": "1.6.6",
	"appid": "wx414706707bc406d4",
	"projectname": "%E5%B0%8F%E4%BD%95%E5%BF%85%E7%9A%84%E6%88%90%E9%95%BF%E5%8E%86%E7%A8%8B",
	"condition": {
		"search": {
			"current": -1,
			"list": []
		},
		"conversation": {
			"current": -1,
			"list": []
		},
		"game": {
			"current": -1,
			"list": []
		},
		"miniprogram": {
			"current": -1,
			"list": []
		}
	}
}